planiverse/__init__.py
planiverse-0.0.0.dist-info/LICENSE
planiverse-0.0.0.dist-info/METADATA
planiverse-0.0.0.dist-info/WHEEL
planiverse-0.0.0.dist-info/top_level.txt
planiverse-0.0.0.dist-info/RECORD
